mathutilspro/__init__.py
mathutilspro/advanced_operations.py
mathutilspro/basic_operations.py
tests/__init__.py
tests/test_advanced_operations.py
tests/test_basic_operations.py
mathutilspro-1.0.0.dist-info/METADATA
mathutilspro-1.0.0.dist-info/WHEEL
mathutilspro-1.0.0.dist-info/top_level.txt
mathutilspro-1.0.0.dist-info/RECORD
